mortal_sign/__init__.py
mortal_sign/main.cpython-39-x86_64-linux-gnu.so
mortal_sign-0.6.2.dist-info/METADATA
mortal_sign-0.6.2.dist-info/WHEEL
mortal_sign-0.6.2.dist-info/entry_points.txt
mortal_sign-0.6.2.dist-info/top_level.txt
mortal_sign-0.6.2.dist-info/RECORD
