Metadata-Version: 2.4
Name: mortal_sign
Version: 0.6.2
Summary: mortal工具集::sign
Home-page: https://www.example.com
Author: Mortal
Author-email: mortal9098@163.com
License: MIT
Classifier: Development Status :: 4 - Beta
Classifier: Programming Language :: Python :: 3
Classifier: Programming Language :: Python :: 3.9
Classifier: Operating System :: POSIX :: Linux
Classifier: Intended Audience :: Developers
Requires-Python: >=3.7
Requires-Dist: click
Requires-Dist: fastapi
Requires-Dist: uvicorn
Requires-Dist: SQLAlchemy
Requires-Dist: PyMySQL
Dynamic: author
Dynamic: author-email
Dynamic: classifier
Dynamic: description
Dynamic: description-content-type
Dynamic: home-page
Dynamic: license
Dynamic: requires-dist
Dynamic: requires-python
Dynamic: summary
